pylint_utils/.external-package
pylint_utils/__init__.py
pylint_utils/__main__.py
pylint_utils/file_scanner.py
pylint_utils/main.py
pylint_utils/py.typed
pylint_utils/pylint_comment_scanner.py
pylint_utils/pylint_suppression_summarizer_plugin.py
pylint_utils/simple_logging.py
pylint_utils/version.py
pylint_utils-0.6.0.dist-info/licenses/LICENSE.txt
pylint_utils-0.6.0.dist-info/METADATA
pylint_utils-0.6.0.dist-info/WHEEL
pylint_utils-0.6.0.dist-info/entry_points.txt
pylint_utils-0.6.0.dist-info/top_level.txt
pylint_utils-0.6.0.dist-info/RECORD
