Metadata-Version: 2.4
Name: pylint_utils
Version: 0.6.0
Summary: Various tools used to examine pylint suppressions and catalog them.
Home-page: https://github.com/jackdewinter/pylint_utils
Author: Jack De Winter
Author-email: jack.de.winter@outlook.com
Maintainer: Jack De Winter
Maintainer-email: jack.de.winter@outlook.com
Project-URL: Documentation, https://pylint_utils.readthedocs.io/
Project-URL: Change Log, https://pylint_utils.readthedocs.io/en/latest/changelog/
Keywords: pylint,code quality,development
Classifier: Development Status :: 4 - Beta
Classifier: Environment :: Console
Classifier: Intended Audience :: Developers
Classifier: Programming Language :: Python :: 3.9
Classifier: Programming Language :: Python :: 3.10
Classifier: Programming Language :: Python :: 3.11
Classifier: Programming Language :: Python :: 3.12
Classifier: Programming Language :: Python :: 3.13
Classifier: License :: OSI Approved :: MIT License
Classifier: Operating System :: OS Independent
Classifier: Natural Language :: English
Classifier: Topic :: Software Development :: Libraries :: Application Frameworks
Requires-Python: >=3.9.0
License-File: LICENSE.txt
Requires-Dist: typing-extensions>=4.5.0
Requires-Dist: columnar>=1.4.1
Dynamic: author
Dynamic: author-email
Dynamic: classifier
Dynamic: description
Dynamic: description-content-type
Dynamic: home-page
Dynamic: keywords
Dynamic: license-file
Dynamic: maintainer
Dynamic: maintainer-email
Dynamic: project-url
Dynamic: requires-dist
Dynamic: requires-python
Dynamic: summary
